Metadata-Version: 2.1
Name: odoo-addon-invoice_line_label_without_internal_ref
Version: 15.0.1.0.0.1
Requires-Python: >=3.8
Requires-Dist: odoo>=15.0a,<15.1dev
Summary: Invoice Line Label Without Internal Reference
Home-page: https://github.com/sygel-technology/sy-account-invoicing
License: AGPL-3
Author: Sygel, Odoo Community Association (OCA)
Author-email: support@odoo-community.org
Classifier: Programming Language :: Python
Classifier: Framework :: Odoo
Classifier: Framework :: Odoo :: 15.0
Classifier: License :: OSI Approved :: GNU Affero General Public License v3
